pastpy/__init__.py
past_by_dev-1.0.0.dist-info/LICENSE
past_by_dev-1.0.0.dist-info/METADATA
past_by_dev-1.0.0.dist-info/WHEEL
past_by_dev-1.0.0.dist-info/top_level.txt
past_by_dev-1.0.0.dist-info/RECORD
