Metadata-Version: 2.1
Name: past-by-dev
Version: 1.0.0
Summary: A past tense package
Home-page: https://github.com/CodeRustyPro/TenseConverter
Author: Dev Shah
Author-email: devpro103@email.com
License: UNKNOWN
Platform: UNKNOWN
Classifier: Programming Language :: Python :: 3
Classifier: License :: OSI Approved :: MIT License
Classifier: Operating System :: OS Independent
